admin_sync/__init__.py
admin_sync/apps.py
admin_sync/collector.py
admin_sync/compat.py
admin_sync/conf.py
admin_sync/datastructures.py
admin_sync/exceptions.py
admin_sync/perms.py
admin_sync/protocol.py
admin_sync/py.typed
admin_sync/signals.py
admin_sync/types.pyi
admin_sync/utils.py
admin_sync/version.py
admin_sync/mixins/__init__.py
admin_sync/mixins/admin.py
admin_sync/mixins/base.py
admin_sync/mixins/pull.py
admin_sync/mixins/push.py
admin_sync/templates/admin/admin_sync/_publish_base.html
admin_sync/templates/admin/admin_sync/publish.html
admin_sync/templates/admin/admin_sync/pull.html
admin_sync/templatetags/__init__.py
admin_sync/templatetags/admin_sync.py
django_admin_sync-0.9.dist-info/METADATA
django_admin_sync-0.9.dist-info/WHEEL
django_admin_sync-0.9.dist-info/licenses/LICENSE
django_admin_sync-0.9.dist-info/RECORD
