Metadata-Version: 2.4
Name: django-admin-sync
Version: 0.9
Author-email: sax <s.apostolico@gmail.com>
License-File: LICENSE
Classifier: Environment :: Web Environment
Classifier: Framework :: Django
Classifier: Framework :: Django :: 3.2
Classifier: Framework :: Django :: 4.2
Classifier: Framework :: Django :: 5.2
Classifier: Intended Audience :: Developers
Classifier: Operating System :: OS Independent
Classifier: Programming Language :: Python :: 3 :: Only
Classifier: Programming Language :: Python :: 3.12
Classifier: Programming Language :: Python :: 3.13
Requires-Python: >=3.12
Requires-Dist: django-admin-extra-buttons>=2.1
Requires-Dist: django-concurrency
Requires-Dist: django-stubs
Requires-Dist: pytz>=2025.1
Requires-Dist: requests
